requestly/__init__.py
requestly/proxy.py
requestly-0.0.2.dist-info/METADATA
requestly-0.0.2.dist-info/WHEEL
requestly-0.0.2.dist-info/entry_points.txt
requestly-0.0.2.dist-info/top_level.txt
requestly-0.0.2.dist-info/RECORD
