Metadata-Version: 2.4
Name: requestly
Version: 0.0.2
Summary: 服务器接口本地代理工具
Author-email: Seven <1162584980@qq.com>
Maintainer-email: Seven <1162584980@qq.com>
License-Expression: MIT
Keywords: requestly,mitmproxy,cli,proxy
Classifier: Environment :: Console
Classifier: Operating System :: OS Independent
Classifier: Programming Language :: Python :: 3
Classifier: Programming Language :: Python :: 3.11
Classifier: Programming Language :: Python :: 3.12
Classifier: Topic :: Utilities
Requires-Python: >=3.11
Requires-Dist: click
Requires-Dist: mitmproxy
Provides-Extra: dev
Requires-Dist: build; extra == "dev"
Requires-Dist: twine; extra == "dev"
Requires-Dist: pytest; extra == "dev"
Requires-Dist: ruff; extra == "dev"
Requires-Dist: black; extra == "dev"
